discord_register/__init__.py
discord_register/_resources.py
discord_register/create.py
discord_register/discordregisterer.py
discord_register/email_class.py
discord_register/exceptions.py
discord_register/utils.py
discord_register_deskent-1.0.0.dist-info/LICENSE
discord_register_deskent-1.0.0.dist-info/METADATA
discord_register_deskent-1.0.0.dist-info/WHEEL
discord_register_deskent-1.0.0.dist-info/top_level.txt
discord_register_deskent-1.0.0.dist-info/RECORD
