Metadata-Version: 2.1
Name: discord-register-deskent
Version: 1.0.0
Summary: Discord account register
Author: Deskent & Vovk-wan
Author-email: battenetciz@gmail.com
Classifier: License :: OSI Approved :: MIT License
Classifier: Programming Language :: Python
Classifier: Programming Language :: Python :: 3
Classifier: Operating System :: OS Independent
Requires-Python: >=3.7
License-File: LICENSE
Requires-Dist: anticaptchaofficial (==1.0.43)
Requires-Dist: aiohttp (==3.8.1)
Requires-Dist: pydantic (==1.9.1)
Requires-Dist: pydantic[email]
Requires-Dist: python-dotenv (==0.19.2)
Requires-Dist: myloguru-deskent (==0.0.12)
